{
    "objectId": "ZTF19abcudso",
    "candidates": [
        {
            "candid": 908427160515015005,
            "jd": 2458662.9271644,
            "ra": 299.3333161,
            "dec": 9.5256407,
            "fid": 1,
            "nid": 908,
            "magpsf": 20.225900650024414,
            "sigmapsf": 0.21989400684833527,
            "magnr": 19.809999465942383,
            "sigmagnr": 0.03700000047683716,
            "magzpsci": 26.322900772094727,
            "isdiffpos": "t",
            "ssdistnr": -999.0,
            "ssnamenr": "-999.0",
            "drb": null
        },
        {
            "candid": 911462650515015005,
            "jd": 2458665.9626505,
            "ra": 299.333321,
            "dec": 9.5256406,
            "fid": 1,
            "nid": 911,
            "magpsf": 19.999500274658203,
            "sigmapsf": 0.2065960019826889,
            "magnr": 19.809999465942383,
            "sigmagnr": 0.03700000047683716,
            "magzpsci": 26.291500091552734,
            "isdiffpos": "t",
            "ssdistnr": -999.0,
            "ssnamenr": "null",
            "drb": null
        },
        {
            "candid": 914298210515015005,
            "jd": 2458668.7982176,
            "ra": 299.3333891,
            "dec": 9.5256659,
            "fid": 1,
            "nid": 914,
            "magpsf": 20.057199478149414,
            "sigmapsf": 0.16218100488185883,
            "magnr": 19.809999465942383,
            "sigmagnr": 0.03700000047683716,
            "magzpsci": 26.294200897216797,
            "isdiffpos": "t",
            "ssdistnr": -999.0,
            "ssnamenr": "null",
            "drb": null
        },
        {
            "candid": 920335100515015003,
            "jd": 2458674.8351042,
            "ra": 299.3333558,
            "dec": 9.5256748,
            "fid": 1,
            "nid": 920,
            "magpsf": 19.81369972229004,
            "sigmapsf": 0.15596100687980652,
            "magnr": 19.809999465942383,
            "sigmagnr": 0.03700000047683716,
            "magzpsci": 26.36669921875,
            "isdiffpos": "t",
            "ssdistnr": -999.0,
            "ssnamenr": "null",
            "drb": null
        },
        {
            "candid": 924307850515015005,
            "jd": 2458678.8078588,
            "ra": 299.3332424,
            "dec": 9.5256863,
            "fid": 1,
            "nid": 924,
            "magpsf": 19.617399215698242,
            "sigmapsf": 0.16708600521087646,
            "magnr": 19.809999465942383,
            "sigmagnr": 0.03700000047683716,
            "magzpsci": 26.2903995513916,
            "isdiffpos": "t",
            "ssdistnr": -999.0,
            "ssnamenr": "null",
            "drb": null
        },
        {
            "candid": 930447520515015006,
            "jd": 2458684.9475231,
            "ra": 299.3333395,
            "dec": 9.5256257,
            "fid": 2,
            "nid": 930,
            "magpsf": 19.7637996673584,
            "sigmapsf": 0.18523399531841278,
            "magnr": 18.934999465942383,
            "sigmagnr": 0.04500000178813934,
            "magzpsci": 26.21179962158203,
            "isdiffpos": "t",
            "ssdistnr": -999.0,
            "ssnamenr": "-999.0",
            "drb": null
        },
        {
            "candid": 937314420515015004,
            "jd": 2458691.8144213,
            "ra": 299.3333143,
            "dec": 9.5256484,
            "fid": 1,
            "nid": 937,
            "magpsf": 20.033599853515625,
            "sigmapsf": 0.1727519929409027,
            "magnr": 19.809999465942383,
            "sigmagnr": 0.03700000047683716,
            "magzpsci": 26.248600006103516,
            "isdiffpos": "t",
            "ssdistnr": -999.0,
            "ssnamenr": "null",
            "drb": null
        },
        {
            "candid": 939331930515015012,
            "jd": 2458693.8319329,
            "ra": 299.3333198,
            "dec": 9.5256473,
            "fid": 1,
            "nid": 939,
            "magpsf": 19.9591007232666,
            "sigmapsf": 0.1322849988937378,
            "magnr": 19.809999465942383,
            "sigmagnr": 0.03700000047683716,
            "magzpsci": 26.28809928894043,
            "isdiffpos": "t",
            "ssdistnr": -999.0,
            "ssnamenr": "null",
            "drb": null
        },
        {
            "candid": 940315940515015014,
            "jd": 2458694.8159491,
            "ra": 299.3333405,
            "dec": 9.5256539,
            "fid": 1,
            "nid": 940,
            "magpsf": 19.957399368286133,
            "sigmapsf": 0.15647299587726593,
            "magnr": 19.809999465942383,
            "sigmagnr": 0.03700000047683716,
            "magzpsci": 26.311399459838867,
            "isdiffpos": "t",
            "ssdistnr": -999.0,
            "ssnamenr": "null",
            "drb": null
        },
        {
            "candid": 946331400515015016,
            "jd": 2458700.8314005,
            "ra": 299.3333533,
            "dec": 9.5256921,
            "fid": 1,
            "nid": 946,
            "magpsf": 20.021099090576172,
            "sigmapsf": 0.1456419974565506,
            "magnr": 19.809999465942383,
            "sigmagnr": 0.03700000047683716,
            "magzpsci": 26.284099578857422,
            "isdiffpos": "t",
            "ssdistnr": -999.0,
            "ssnamenr": "null",
            "drb": null
        },
        {
            "candid": 2297482070515015009,
            "jd": 2460051.9820718,
            "ra": 299.3333628,
            "dec": 9.5257313,
            "fid": 1,
            "nid": 2297,
            "magpsf": 20.332300186157227,
            "sigmapsf": 0.2532849907875061,
            "magnr": 19.809999465942383,
            "sigmagnr": 0.03700000047683716,
            "magzpsci": 26.404300689697266,
            "isdiffpos": "t",
            "ssdistnr": null,
            "ssnamenr": null,
            "drb": null
        },
        {
            "candid": 2300451290515015006,
            "jd": 2460054.9512963,
            "ra": 299.3333551,
            "dec": 9.5257238,
            "fid": 1,
            "nid": 2300,
            "magpsf": 20.153499603271484,
            "sigmapsf": 0.19638200104236603,
            "magnr": 19.809999465942383,
            "sigmagnr": 0.03700000047683716,
            "magzpsci": 26.3435001373291,
            "isdiffpos": "t",
            "ssdistnr": null,
            "ssnamenr": null,
            "drb": null
        },
        {
            "candid": 2302457930515015005,
            "jd": 2460056.9579398,
            "ra": 299.3332215,
            "dec": 9.5257375,
            "fid": 1,
            "nid": 2302,
            "magpsf": 20.30229949951172,
            "sigmapsf": 0.20944899320602417,
            "magnr": 19.809999465942383,
            "sigmagnr": 0.03700000047683716,
            "magzpsci": 26.364299774169922,
            "isdiffpos": "t",
            "ssdistnr": null,
            "ssnamenr": null,
            "drb": null
        },
        {
            "candid": 2304455650515015005,
            "jd": 2460058.9556597,
            "ra": 299.3332777,
            "dec": 9.525696,
            "fid": 2,
            "nid": 2304,
            "magpsf": 20.00189971923828,
            "sigmapsf": 0.16175900399684906,
            "magnr": 18.934999465942383,
            "sigmagnr": 0.04500000178813934,
            "magzpsci": 26.21190071105957,
            "isdiffpos": "t",
            "ssdistnr": null,
            "ssnamenr": null,
            "drb": null
        },
        {
            "candid": 2306426270515015012,
            "jd": 2460060.9262731,
            "ra": 299.3333711,
            "dec": 9.5256334,
            "fid": 1,
            "nid": 2306,
            "magpsf": 20.2101993560791,
            "sigmapsf": 0.23878100514411926,
            "magnr": 19.809999465942383,
            "sigmagnr": 0.03700000047683716,
            "magzpsci": 26.230199813842773,
            "isdiffpos": "t",
            "ssdistnr": null,
            "ssnamenr": null,
            "drb": null
        },
        {
            "candid": 2311460890515015007,
            "jd": 2460065.9608912,
            "ra": 299.3332826,
            "dec": 9.5256812,
            "fid": 1,
            "nid": 2311,
            "magpsf": 19.896699905395508,
            "sigmapsf": 0.204476997256279,
            "magnr": 19.809999465942383,
            "sigmagnr": 0.03700000047683716,
            "magzpsci": 26.317699432373047,
            "isdiffpos": "t",
            "ssdistnr": null,
            "ssnamenr": null,
            "drb": null
        },
        {
            "candid": 2323412490515015007,
            "jd": 2460077.9125,
            "ra": 299.3333411,
            "dec": 9.525702,
            "fid": 1,
            "nid": 2323,
            "magpsf": 19.79990005493164,
            "sigmapsf": 0.16938699781894684,
            "magnr": 19.809999465942383,
            "sigmagnr": 0.03700000047683716,
            "magzpsci": 26.331899642944336,
            "isdiffpos": "t",
            "ssdistnr": null,
            "ssnamenr": null,
            "drb": null
        },
        {
            "candid": 2325433980515015005,
            "jd": 2460079.9339815,
            "ra": 299.3333186,
            "dec": 9.525664,
            "fid": 2,
            "nid": 2325,
            "magpsf": 19.881399154663086,
            "sigmapsf": 0.13877099752426147,
            "magnr": 18.934999465942383,
            "sigmagnr": 0.04500000178813934,
            "magzpsci": 26.34040069580078,
            "isdiffpos": "t",
            "ssdistnr": null,
            "ssnamenr": null,
            "drb": null
        },
        {
            "candid": 2325448860515015006,
            "jd": 2460079.9488657,
            "ra": 299.3333304,
            "dec": 9.5256573,
            "fid": 1,
            "nid": 2325,
            "magpsf": 19.907699584960938,
            "sigmapsf": 0.17267699539661407,
            "magnr": 19.809999465942383,
            "sigmagnr": 0.03700000047683716,
            "magzpsci": 26.367700576782227,
            "isdiffpos": "t",
            "ssdistnr": null,
            "ssnamenr": null,
            "drb": null
        },
        {
            "candid": 2328423630515015010,
            "jd": 2460082.9236343,
            "ra": 299.3333606,
            "dec": 9.525639,
            "fid": 1,
            "nid": 2328,
            "magpsf": 20.007699966430664,
            "sigmapsf": 0.1772419959306717,
            "magnr": 19.809999465942383,
            "sigmagnr": 0.03700000047683716,
            "magzpsci": 26.31170082092285,
            "isdiffpos": "t",
            "ssdistnr": null,
            "ssnamenr": null,
            "drb": null
        },
        {
            "candid": 2328444140515015013,
            "jd": 2460082.9441435,
            "ra": 299.3332607,
            "dec": 9.5256875,
            "fid": 2,
            "nid": 2328,
            "magpsf": 20.176799774169922,
            "sigmapsf": 0.18541599810123444,
            "magnr": 18.934999465942383,
            "sigmagnr": 0.04500000178813934,
            "magzpsci": 26.32080078125,
            "isdiffpos": "t",
            "ssdistnr": null,
            "ssnamenr": null,
            "drb": null
        },
        {
            "candid": 2330404380515015010,
            "jd": 2460084.9043866,
            "ra": 299.3332467,
            "dec": 9.5256534,
            "fid": 2,
            "nid": 2330,
            "magpsf": 20.127500534057617,
            "sigmapsf": 0.18235300481319427,
            "magnr": 18.934999465942383,
            "sigmagnr": 0.04500000178813934,
            "magzpsci": 26.238500595092773,
            "isdiffpos": "t",
            "ssdistnr": null,
            "ssnamenr": null,
            "drb": null
        },
        {
            "candid": 2330427680515015009,
            "jd": 2460084.9276852,
            "ra": 299.3333227,
            "dec": 9.5255945,
            "fid": 1,
            "nid": 2330,
            "magpsf": 20.07979965209961,
            "sigmapsf": 0.20281000435352325,
            "magnr": 19.809999465942383,
            "sigmagnr": 0.03700000047683716,
            "magzpsci": 26.264799118041992,
            "isdiffpos": "t",
            "ssdistnr": null,
            "ssnamenr": null,
            "drb": null
        },
        {
            "candid": 2332427020515015009,
            "jd": 2460086.9270255,
            "ra": 299.3332995,
            "dec": 9.5256639,
            "fid": 1,
            "nid": 2332,
            "magpsf": 19.999900817871094,
            "sigmapsf": 0.15551699697971344,
            "magnr": 19.809999465942383,
            "sigmagnr": 0.03700000047683716,
            "magzpsci": 26.38990020751953,
            "isdiffpos": "t",
            "ssdistnr": null,
            "ssnamenr": null,
            "drb": null
        },
        {
            "candid": 2334447890515015006,
            "jd": 2460088.9478935,
            "ra": 299.3333758,
            "dec": 9.5256358,
            "fid": 1,
            "nid": 2334,
            "magpsf": 20.169700622558594,
            "sigmapsf": 0.1621609926223755,
            "magnr": 19.809999465942383,
            "sigmagnr": 0.03700000047683716,
            "magzpsci": 26.439699172973633,
            "isdiffpos": "t",
            "ssdistnr": null,
            "ssnamenr": null,
            "drb": null
        },
        {
            "candid": 2339443180515015011,
            "jd": 2460093.9431829,
            "ra": 299.3333562,
            "dec": 9.5256652,
            "fid": 1,
            "nid": 2339,
            "magpsf": 20.323579788208008,
            "sigmapsf": 0.18459661304950714,
            "magnr": 19.809999465942383,
            "sigmagnr": 0.03700000047683716,
            "magzpsci": 26.38758087158203,
            "isdiffpos": "t",
            "ssdistnr": -999.0,
            "ssnamenr": "null",
            "drb": null
        },
        {
            "candid": 2470128130515015008,
            "jd": 2460224.6281366,
            "ra": 299.3333491,
            "dec": 9.5257195,
            "fid": 1,
            "nid": 2470,
            "magpsf": 20.163721084594727,
            "sigmapsf": 0.21666695177555084,
            "magnr": 19.809999465942383,
            "sigmagnr": 0.03700000047683716,
            "magzpsci": 26.45172119140625,
            "isdiffpos": "t",
            "ssdistnr": -999.0,
            "ssnamenr": "null",
            "drb": 1.0
        },
        {
            "candid": 2614546904015015012,
            "jd": 2460369.0469097,
            "ra": 299.333337,
            "dec": 9.5256718,
            "fid": 2,
            "nid": 2614,
            "magpsf": 19.630599975585938,
            "sigmapsf": 0.18987900018692017,
            "magnr": 19.086999893188477,
            "sigmagnr": 0.06300000101327896,
            "magzpsci": 26.29759979248047,
            "isdiffpos": "t",
            "ssdistnr": null,
            "ssnamenr": null,
            "drb": null
        },
        {
            "candid": 2614547374015015007,
            "jd": 2460369.0473727,
            "ra": 299.3333182,
            "dec": 9.5257155,
            "fid": 2,
            "nid": 2614,
            "magpsf": 19.441999435424805,
            "sigmapsf": 0.1802780032157898,
            "magnr": 19.086999893188477,
            "sigmagnr": 0.06300000101327896,
            "magzpsci": 26.304000854492188,
            "isdiffpos": "t",
            "ssdistnr": null,
            "ssnamenr": null,
            "drb": null
        },
        {
            "candid": 2614547844015015010,
            "jd": 2460369.0478472,
            "ra": 299.3332947,
            "dec": 9.5256485,
            "fid": 2,
            "nid": 2614,
            "magpsf": 19.62420082092285,
            "sigmapsf": 0.19687999784946442,
            "magnr": 19.086999893188477,
            "sigmagnr": 0.06300000101327896,
            "magzpsci": 26.305200576782227,
            "isdiffpos": "t",
            "ssdistnr": null,
            "ssnamenr": null,
            "drb": null
        },
        {
            "candid": 2615544814015015009,
            "jd": 2460370.0448148,
            "ra": 299.3332741,
            "dec": 9.5256878,
            "fid": 2,
            "nid": 2615,
            "magpsf": 19.759357452392578,
            "sigmapsf": 0.20153507590293884,
            "magnr": 19.086999893188477,
            "sigmagnr": 0.06300000101327896,
            "magzpsci": 26.352357864379883,
            "isdiffpos": "t",
            "ssdistnr": -999.0,
            "ssnamenr": "null",
            "drb": null
        },
        {
            "candid": 2650490320515015008,
            "jd": 2460404.9903241,
            "ra": 299.3332652,
            "dec": 9.5256563,
            "fid": 2,
            "nid": 2650,
            "magpsf": 20.083499908447266,
            "sigmapsf": 0.15544399619102478,
            "magnr": 18.934999465942383,
            "sigmagnr": 0.04500000178813934,
            "magzpsci": 26.33449935913086,
            "isdiffpos": "t",
            "ssdistnr": null,
            "ssnamenr": null,
            "drb": 0.9967893362045288
        },
        {
            "candid": 2666402040515015006,
            "jd": 2460420.9020486,
            "ra": 299.333223,
            "dec": 9.525839,
            "fid": 2,
            "nid": 2666,
            "magpsf": 19.555299758911133,
            "sigmapsf": 0.17070099711418152,
            "magnr": 18.934999465942383,
            "sigmagnr": 0.04500000178813934,
            "magzpsci": 26.229299545288086,
            "isdiffpos": "t",
            "ssdistnr": null,
            "ssnamenr": null,
            "drb": null
        },
        {
            "candid": 2666466580515015007,
            "jd": 2460420.9665856,
            "ra": 299.3333104,
            "dec": 9.525697,
            "fid": 1,
            "nid": 2666,
            "magpsf": 19.641199111938477,
            "sigmapsf": 0.1603509932756424,
            "magnr": 19.809999465942383,
            "sigmagnr": 0.03700000047683716,
            "magzpsci": 26.353200912475586,
            "isdiffpos": "t",
            "ssdistnr": null,
            "ssnamenr": null,
            "drb": null
        },
        {
            "candid": 2679467730515015008,
            "jd": 2460433.9677315,
            "ra": 299.3333205,
            "dec": 9.5257393,
            "fid": 1,
            "nid": 2679,
            "magpsf": 19.56130027770996,
            "sigmapsf": 0.10880699753761292,
            "magnr": 19.809999465942383,
            "sigmagnr": 0.03700000047683716,
            "magzpsci": 26.34630012512207,
            "isdiffpos": "t",
            "ssdistnr": null,
            "ssnamenr": null,
            "drb": null
        },
        {
            "candid": 2687426060515015011,
            "jd": 2460441.9260648,
            "ra": 299.3332945,
            "dec": 9.5256529,
            "fid": 2,
            "nid": 2687,
            "magpsf": 19.434200286865234,
            "sigmapsf": 0.15426599979400635,
            "magnr": 18.934999465942383,
            "sigmagnr": 0.04500000178813934,
            "magzpsci": 26.332199096679688,
            "isdiffpos": "t",
            "ssdistnr": null,
            "ssnamenr": null,
            "drb": null
        },
        {
            "candid": 2687470060515015011,
            "jd": 2460441.9700694,
            "ra": 299.333343,
            "dec": 9.5257059,
            "fid": 1,
            "nid": 2687,
            "magpsf": 19.60569953918457,
            "sigmapsf": 0.11624400317668915,
            "magnr": 19.809999465942383,
            "sigmagnr": 0.03700000047683716,
            "magzpsci": 26.413700103759766,
            "isdiffpos": "t",
            "ssdistnr": null,
            "ssnamenr": null,
            "drb": null
        },
        {
            "candid": 2696402160515015010,
            "jd": 2460450.9021644,
            "ra": 299.333352,
            "dec": 9.5256882,
            "fid": 2,
            "nid": 2696,
            "magpsf": 19.520000457763672,
            "sigmapsf": 0.1450739949941635,
            "magnr": 18.934999465942383,
            "sigmagnr": 0.04500000178813934,
            "magzpsci": 26.34000015258789,
            "isdiffpos": "t",
            "ssdistnr": null,
            "ssnamenr": null,
            "drb": null
        },
        {
            "candid": 2698405520515015007,
            "jd": 2460452.9055208,
            "ra": 299.3332914,
            "dec": 9.5257443,
            "fid": 2,
            "nid": 2698,
            "magpsf": 19.713899612426758,
            "sigmapsf": 0.18277199566364288,
            "magnr": 18.934999465942383,
            "sigmagnr": 0.04500000178813934,
            "magzpsci": 26.237899780273438,
            "isdiffpos": "t",
            "ssdistnr": null,
            "ssnamenr": null,
            "drb": null
        },
        {
            "candid": 2705426700515015008,
            "jd": 2460459.9267014,
            "ra": 299.3332901,
            "dec": 9.5256791,
            "fid": 1,
            "nid": 2705,
            "magpsf": 19.64259910583496,
            "sigmapsf": 0.1650020033121109,
            "magnr": 19.809999465942383,
            "sigmagnr": 0.03700000047683716,
            "magzpsci": 26.38759994506836,
            "isdiffpos": "t",
            "ssdistnr": null,
            "ssnamenr": null,
            "drb": null
        },
        {
            "candid": 2709441520515015009,
            "jd": 2460463.9415278,
            "ra": 299.3333274,
            "dec": 9.5256705,
            "fid": 1,
            "nid": 2709,
            "magpsf": 19.785499572753906,
            "sigmapsf": 0.16306200623512268,
            "magnr": 19.809999465942383,
            "sigmagnr": 0.03700000047683716,
            "magzpsci": 26.423500061035156,
            "isdiffpos": "t",
            "ssdistnr": null,
            "ssnamenr": null,
            "drb": null
        },
        {
            "candid": 2718378260515015008,
            "jd": 2460472.8782639,
            "ra": 299.3333279,
            "dec": 9.5256546,
            "fid": 2,
            "nid": 2718,
            "magpsf": 19.792699813842773,
            "sigmapsf": 0.13937200605869293,
            "magnr": 18.934999465942383,
            "sigmagnr": 0.04500000178813934,
            "magzpsci": 26.354700088500977,
            "isdiffpos": "t",
            "ssdistnr": null,
            "ssnamenr": null,
            "drb": null
        },
        {
            "candid": 2718441720515015006,
            "jd": 2460472.9417245,
            "ra": 299.3332788,
            "dec": 9.5256846,
            "fid": 1,
            "nid": 2718,
            "magpsf": 19.829500198364258,
            "sigmapsf": 0.15408700704574585,
            "magnr": 19.809999465942383,
            "sigmagnr": 0.03700000047683716,
            "magzpsci": 26.398500442504883,
            "isdiffpos": "t",
            "ssdistnr": null,
            "ssnamenr": null,
            "drb": null
        },
        {
            "candid": 2720387690515015009,
            "jd": 2460474.8876968,
            "ra": 299.3333573,
            "dec": 9.52571,
            "fid": 2,
            "nid": 2720,
            "magpsf": 19.807300567626953,
            "sigmapsf": 0.15018700063228607,
            "magnr": 18.934999465942383,
            "sigmagnr": 0.04500000178813934,
            "magzpsci": 26.362300872802734,
            "isdiffpos": "t",
            "ssdistnr": null,
            "ssnamenr": null,
            "drb": null
        },
        {
            "candid": 2720422340515015010,
            "jd": 2460474.9223495,
            "ra": 299.3333479,
            "dec": 9.5256369,
            "fid": 1,
            "nid": 2720,
            "magpsf": 19.90290069580078,
            "sigmapsf": 0.1643970012664795,
            "magnr": 19.809999465942383,
            "sigmagnr": 0.03700000047683716,
            "magzpsci": 26.418899536132812,
            "isdiffpos": "t",
            "ssdistnr": null,
            "ssnamenr": null,
            "drb": null
        },
        {
            "candid": 2722378830515015009,
            "jd": 2460476.878831,
            "ra": 299.3333229,
            "dec": 9.5256795,
            "fid": 1,
            "nid": 2722,
            "magpsf": 19.858400344848633,
            "sigmapsf": 0.16954100131988525,
            "magnr": 19.809999465942383,
            "sigmagnr": 0.03700000047683716,
            "magzpsci": 26.431400299072266,
            "isdiffpos": "t",
            "ssdistnr": null,
            "ssnamenr": null,
            "drb": null
        },
        {
            "candid": 2725400040515015007,
            "jd": 2460479.9000463,
            "ra": 299.3332655,
            "dec": 9.5255832,
            "fid": 1,
            "nid": 2725,
            "magpsf": 20.082799911499023,
            "sigmapsf": 0.23350399732589722,
            "magnr": 19.809999465942383,
            "sigmagnr": 0.03700000047683716,
            "magzpsci": 26.427799224853516,
            "isdiffpos": "t",
            "ssdistnr": null,
            "ssnamenr": null,
            "drb": null
        },
        {
            "candid": 2736375050515015007,
            "jd": 2460490.8750579,
            "ra": 299.3333174,
            "dec": 9.5257052,
            "fid": 1,
            "nid": 2736,
            "magpsf": 19.835500717163086,
            "sigmapsf": 0.16516900062561035,
            "magnr": 19.809999465942383,
            "sigmagnr": 0.03700000047683716,
            "magzpsci": 26.4424991607666,
            "isdiffpos": "t",
            "ssdistnr": null,
            "ssnamenr": null,
            "drb": null
        },
        {
            "candid": 2740357090515015012,
            "jd": 2460494.8570949,
            "ra": 299.3332815,
            "dec": 9.5256751,
            "fid": 2,
            "nid": 2740,
            "magpsf": 19.889299392700195,
            "sigmapsf": 0.15197299420833588,
            "magnr": 18.934999465942383,
            "sigmagnr": 0.04500000178813934,
            "magzpsci": 26.372299194335938,
            "isdiffpos": "t",
            "ssdistnr": null,
            "ssnamenr": null,
            "drb": null
        },
        {
            "candid": 2746353700515015011,
            "jd": 2460500.8537037,
            "ra": 299.3333772,
            "dec": 9.5256731,
            "fid": 1,
            "nid": 2746,
            "magpsf": 19.977100372314453,
            "sigmapsf": 0.2151000052690506,
            "magnr": 19.809999465942383,
            "sigmagnr": 0.03700000047683716,
            "magzpsci": 26.385099411010742,
            "isdiffpos": "t",
            "ssdistnr": null,
            "ssnamenr": null,
            "drb": null
        },
        {
            "candid": 2753354340515015009,
            "jd": 2460507.8543403,
            "ra": 299.3333286,
            "dec": 9.5256479,
            "fid": 1,
            "nid": 2753,
            "magpsf": 20.287799835205078,
            "sigmapsf": 0.1933860033750534,
            "magnr": 19.809999465942383,
            "sigmagnr": 0.03700000047683716,
            "magzpsci": 26.378799438476562,
            "isdiffpos": "t",
            "ssdistnr": null,
            "ssnamenr": null,
            "drb": null
        },
        {
            "candid": 2755431700515015008,
            "jd": 2460509.9317014,
            "ra": 299.3333087,
            "dec": 9.5257021,
            "fid": 1,
            "nid": 2755,
            "magpsf": 20.306900024414062,
            "sigmapsf": 0.2618570029735565,
            "magnr": 19.809999465942383,
            "sigmagnr": 0.03700000047683716,
            "magzpsci": 26.23189926147461,
            "isdiffpos": "t",
            "ssdistnr": null,
            "ssnamenr": null,
            "drb": null
        },
        {
            "candid": 2764413770515015017,
            "jd": 2460518.9137731,
            "ra": 299.3332755,
            "dec": 9.5256971,
            "fid": 1,
            "nid": 2764,
            "magpsf": 20.238500595092773,
            "sigmapsf": 0.24912500381469727,
            "magnr": 19.809999465942383,
            "sigmagnr": 0.03700000047683716,
            "magzpsci": 26.36750030517578,
            "isdiffpos": "t",
            "ssdistnr": null,
            "ssnamenr": null,
            "drb": null
        },
        {
            "candid": 2775295090515015013,
            "jd": 2460529.7950926,
            "ra": 299.3332865,
            "dec": 9.5256745,
            "fid": 1,
            "nid": 2775,
            "magpsf": 20.231199264526367,
            "sigmapsf": 0.1691640019416809,
            "magnr": 19.809999465942383,
            "sigmagnr": 0.03700000047683716,
            "magzpsci": 26.327199935913086,
            "isdiffpos": "t",
            "ssdistnr": null,
            "ssnamenr": null,
            "drb": null
        },
        {
            "candid": 2777297540515015016,
            "jd": 2460531.7975463,
            "ra": 299.3333453,
            "dec": 9.5256804,
            "fid": 1,
            "nid": 2777,
            "magpsf": 20.24846649169922,
            "sigmapsf": 0.2102319896221161,
            "magnr": 19.809999465942383,
            "sigmagnr": 0.03700000047683716,
            "magzpsci": 26.348466873168945,
            "isdiffpos": "t",
            "ssdistnr": -999.0,
            "ssnamenr": "null",
            "drb": null
        },
        {
            "candid": 2777297540515025016,
            "jd": 2460531.7975463,
            "ra": 299.3333453,
            "dec": 9.5256804,
            "fid": 1,
            "nid": 2777,
            "magpsf": 20.24850082397461,
            "sigmapsf": 0.21023200452327728,
            "magnr": 19.809999465942383,
            "sigmagnr": 0.03700000047683716,
            "magzpsci": 26.348499298095703,
            "isdiffpos": "t",
            "ssdistnr": null,
            "ssnamenr": null,
            "drb": null
        },
        {
            "candid": 2791204730515015005,
            "jd": 2460545.7047338,
            "ra": 299.3333798,
            "dec": 9.5257132,
            "fid": 1,
            "nid": 2791,
            "magpsf": 20.06220054626465,
            "sigmapsf": 0.24237699806690216,
            "magnr": 19.809999465942383,
            "sigmagnr": 0.03700000047683716,
            "magzpsci": 26.449199676513672,
            "isdiffpos": "t",
            "ssdistnr": null,
            "ssnamenr": null,
            "drb": null
        },
        {
            "candid": 2793235600515015009,
            "jd": 2460547.7356019,
            "ra": 299.3333636,
            "dec": 9.5257183,
            "fid": 2,
            "nid": 2793,
            "magpsf": 20.156400680541992,
            "sigmapsf": 0.17511500418186188,
            "magnr": 18.934999465942383,
            "sigmagnr": 0.04500000178813934,
            "magzpsci": 26.382400512695312,
            "isdiffpos": "t",
            "ssdistnr": null,
            "ssnamenr": null,
            "drb": null
        },
        {
            "candid": 2799212750515015006,
            "jd": 2460553.7127546,
            "ra": 299.3333352,
            "dec": 9.5256557,
            "fid": 1,
            "nid": 2799,
            "magpsf": 20.248199462890625,
            "sigmapsf": 0.2204499989748001,
            "magnr": 19.809999465942383,
            "sigmagnr": 0.03700000047683716,
            "magzpsci": 26.428199768066406,
            "isdiffpos": "t",
            "ssdistnr": null,
            "ssnamenr": null,
            "drb": null
        },
        {
            "candid": 2802233440515015008,
            "jd": 2460556.7334491,
            "ra": 299.3333144,
            "dec": 9.5256429,
            "fid": 1,
            "nid": 2802,
            "magpsf": 20.166900634765625,
            "sigmapsf": 0.20231199264526367,
            "magnr": 19.809999465942383,
            "sigmagnr": 0.03700000047683716,
            "magzpsci": 26.386899948120117,
            "isdiffpos": "t",
            "ssdistnr": null,
            "ssnamenr": null,
            "drb": null
        },
        {
            "candid": 2810266790515015006,
            "jd": 2460564.766794,
            "ra": 299.3333752,
            "dec": 9.5257076,
            "fid": 1,
            "nid": 2810,
            "magpsf": 20.088056564331055,
            "sigmapsf": 0.16831041872501373,
            "magnr": 19.809999465942383,
            "sigmagnr": 0.03700000047683716,
            "magzpsci": 26.380056381225586,
            "isdiffpos": "t",
            "ssdistnr": -999.0,
            "ssnamenr": "null",
            "drb": null
        },
        {
            "jd": 2458639.90282,
            "fid": 2,
            "diffmaglim": 20.795000076293945
        },
        {
            "jd": 2458642.9011,
            "fid": 1,
            "diffmaglim": 21.07900047302246
        },
        {
            "jd": 2458642.94155,
            "fid": 2,
            "diffmaglim": 20.77199935913086
        },
        {
            "jd": 2458645.92093,
            "fid": 1,
            "diffmaglim": 20.827999114990234
        },
        {
            "jd": 2458645.97097,
            "fid": 2,
            "diffmaglim": 20.691999435424805
        },
        {
            "jd": 2458648.94322,
            "fid": 1,
            "diffmaglim": 20.12700080871582
        },
        {
            "jd": 2458648.97361,
            "fid": 2,
            "diffmaglim": 20.349000930786133
        },
        {
            "jd": 2458651.92144,
            "fid": 2,
            "diffmaglim": 19.500999450683594
        },
        {
            "jd": 2458654.81488,
            "fid": 1,
            "diffmaglim": 19.535999298095703
        },
        {
            "jd": 2458654.89764,
            "fid": 2,
            "diffmaglim": 19.47800064086914
        },
        {
            "jd": 2458655.79405,
            "fid": 1,
            "diffmaglim": 19.215999603271484
        },
        {
            "jd": 2458655.8778,
            "fid": 2,
            "diffmaglim": 19.3799991607666
        },
        {
            "jd": 2458657.89912,
            "fid": 2,
            "diffmaglim": 20.187999725341797
        },
        {
            "jd": 2458658.88297,
            "fid": 2,
            "diffmaglim": 20.615999221801758
        },
        {
            "jd": 2458660.96481,
            "fid": 2,
            "diffmaglim": 19.972999572753906
        },
        {
            "jd": 2458661.85352,
            "fid": 2,
            "diffmaglim": 20.733999252319336
        },
        {
            "jd": 2458661.95669,
            "fid": 1,
            "diffmaglim": 20.461999893188477
        },
        {
            "jd": 2458662.82155,
            "fid": 2,
            "diffmaglim": 20.844999313354492
        },
        {
            "jd": 2458663.85459,
            "fid": 2,
            "diffmaglim": 20.413999557495117
        },
        {
            "jd": 2458663.95795,
            "fid": 1,
            "diffmaglim": 20.312999725341797
        },
        {
            "jd": 2458665.92318,
            "fid": 2,
            "diffmaglim": 20.783000946044922
        },
        {
            "jd": 2458671.86255,
            "fid": 1,
            "diffmaglim": 15.87600040435791
        },
        {
            "jd": 2458674.80181,
            "fid": 2,
            "diffmaglim": 20.586000442504883
        },
        {
            "jd": 2458677.81134,
            "fid": 2,
            "diffmaglim": 20.35700035095215
        },
        {
            "jd": 2458677.83765,
            "fid": 1,
            "diffmaglim": 19.992000579833984
        },
        {
            "jd": 2458680.82771,
            "fid": 2,
            "diffmaglim": 19.434999465942383
        },
        {
            "jd": 2458680.94821,
            "fid": 1,
            "diffmaglim": 19.04599952697754
        },
        {
            "jd": 2458688.8165,
            "fid": 1,
            "diffmaglim": 20.493999481201172
        },
        {
            "jd": 2458688.87507,
            "fid": 2,
            "diffmaglim": 20.600000381469727
        },
        {
            "jd": 2458691.87779,
            "fid": 2,
            "diffmaglim": 20.781999588012695
        },
        {
            "jd": 2458694.83936,
            "fid": 2,
            "diffmaglim": 20.187000274658203
        },
        {
            "jd": 2458697.88045,
            "fid": 2,
            "diffmaglim": 20.743999481201172
        },
        {
            "jd": 2460032.9489815,
            "fid": 2,
            "diffmaglim": 19.77829933166504
        },
        {
            "jd": 2460042.9640162,
            "fid": 2,
            "diffmaglim": 19.693899154663086
        },
        {
            "jd": 2460044.9222454,
            "fid": 2,
            "diffmaglim": 19.665599822998047
        },
        {
            "jd": 2460044.9832523,
            "fid": 1,
            "diffmaglim": 19.71660041809082
        },
        {
            "jd": 2460046.9662847,
            "fid": 1,
            "diffmaglim": 17.480300903320312
        },
        {
            "jd": 2460047.016875,
            "fid": 2,
            "diffmaglim": 18.29640007019043
        },
        {
            "jd": 2460051.9537269,
            "fid": 2,
            "diffmaglim": 20.601299285888672
        },
        {
            "jd": 2460056.9822338,
            "fid": 2,
            "diffmaglim": 20.741300582885742
        },
        {
            "jd": 2460060.9709144,
            "fid": 2,
            "diffmaglim": 20.257600784301758
        },
        {
            "jd": 2460062.9686806,
            "fid": 2,
            "diffmaglim": 20.702199935913086
        },
        {
            "jd": 2460065.9206019,
            "fid": 2,
            "diffmaglim": 19.72010040283203
        },
        {
            "jd": 2460073.8983218,
            "fid": 2,
            "diffmaglim": 19.34709930419922
        },
        {
            "jd": 2460073.9203588,
            "fid": 1,
            "diffmaglim": 19.15220069885254
        },
        {
            "jd": 2460077.9618866,
            "fid": 2,
            "diffmaglim": 20.130599975585938
        },
        {
            "jd": 2460086.9044097,
            "fid": 2,
            "diffmaglim": 20.712799072265625
        },
        {
            "jd": 2460088.9003009,
            "fid": 2,
            "diffmaglim": 20.36840057373047
        },
        {
            "jd": 2460090.9443866,
            "fid": 2,
            "diffmaglim": 19.950899124145508
        },
        {
            "jd": 2460093.9004514,
            "fid": 2,
            "diffmaglim": 20.808900833129883
        },
        {
            "jd": 2460195.6850463,
            "fid": 1,
            "diffmaglim": 20.874500274658203
        },
        {
            "jd": 2460195.7346181,
            "fid": 2,
            "diffmaglim": 20.718900680541992
        },
        {
            "jd": 2460198.7283912,
            "fid": 1,
            "diffmaglim": 20.65130043029785
        },
        {
            "jd": 2460198.7675926,
            "fid": 2,
            "diffmaglim": 20.442399978637695
        },
        {
            "jd": 2460201.6717824,
            "fid": 2,
            "diffmaglim": 20.756999969482422
        },
        {
            "jd": 2460201.7143403,
            "fid": 1,
            "diffmaglim": 20.580699920654297
        },
        {
            "jd": 2460203.7140741,
            "fid": 2,
            "diffmaglim": 20.85890007019043
        },
        {
            "jd": 2460203.7585417,
            "fid": 1,
            "diffmaglim": 20.95840072631836
        },
        {
            "jd": 2460205.6512384,
            "fid": 1,
            "diffmaglim": 21.073999404907227
        },
        {
            "jd": 2460205.6703704,
            "fid": 2,
            "diffmaglim": 20.936800003051758
        },
        {
            "jd": 2460207.6856944,
            "fid": 2,
            "diffmaglim": 20.903400421142578
        },
        {
            "jd": 2460207.6916435,
            "fid": 1,
            "diffmaglim": 20.75670051574707
        },
        {
            "jd": 2460209.7031134,
            "fid": 2,
            "diffmaglim": 18.79450035095215
        },
        {
            "jd": 2460209.7506713,
            "fid": 1,
            "diffmaglim": 20.020700454711914
        },
        {
            "jd": 2460212.6715972,
            "fid": 2,
            "diffmaglim": 20.301000595092773
        },
        {
            "jd": 2460212.7250579,
            "fid": 1,
            "diffmaglim": 19.783000946044922
        },
        {
            "jd": 2460214.6493171,
            "fid": 1,
            "diffmaglim": 19.436800003051758
        },
        {
            "jd": 2460214.6876157,
            "fid": 2,
            "diffmaglim": 19.89389991760254
        },
        {
            "jd": 2460216.6309259,
            "fid": 2,
            "diffmaglim": 20.168100357055664
        },
        {
            "jd": 2460216.6929514,
            "fid": 1,
            "diffmaglim": 19.64579963684082
        },
        {
            "jd": 2460220.6901389,
            "fid": 1,
            "diffmaglim": 19.704500198364258
        },
        {
            "jd": 2460222.6271181,
            "fid": 2,
            "diffmaglim": 20.11280059814453
        },
        {
            "jd": 2460222.7023727,
            "fid": 1,
            "diffmaglim": 20.146099090576172
        },
        {
            "jd": 2460352.0699537,
            "fid": 2,
            "diffmaglim": 17.939800262451172
        },
        {
            "jd": 2460353.068206,
            "fid": 2,
            "diffmaglim": 17.875699996948242
        },
        {
            "jd": 2460353.0686806,
            "fid": 2,
            "diffmaglim": 17.535900115966797
        },
        {
            "jd": 2460353.0691435,
            "fid": 2,
            "diffmaglim": 17.791900634765625
        },
        {
            "jd": 2460354.0679398,
            "fid": 2,
            "diffmaglim": 18.421100616455078
        },
        {
            "jd": 2460354.0684028,
            "fid": 2,
            "diffmaglim": 18.37070083618164
        },
        {
            "jd": 2460355.064456,
            "fid": 2,
            "diffmaglim": 18.920499801635742
        },
        {
            "jd": 2460355.0649306,
            "fid": 2,
            "diffmaglim": 18.88599967956543
        },
        {
            "jd": 2460355.0653935,
            "fid": 2,
            "diffmaglim": 18.830799102783203
        },
        {
            "jd": 2460356.0635764,
            "fid": 2,
            "diffmaglim": 19.133399963378906
        },
        {
            "jd": 2460356.0640509,
            "fid": 2,
            "diffmaglim": 19.151899337768555
        },
        {
            "jd": 2460356.0645255,
            "fid": 2,
            "diffmaglim": 19.212900161743164
        },
        {
            "jd": 2460357.0664583,
            "fid": 2,
            "diffmaglim": 18.709400177001953
        },
        {
            "jd": 2460358.0627315,
            "fid": 2,
            "diffmaglim": 19.2362003326416
        },
        {
            "jd": 2460358.063206,
            "fid": 2,
            "diffmaglim": 19.290000915527344
        },
        {
            "jd": 2460358.063669,
            "fid": 2,
            "diffmaglim": 19.27739906311035
        },
        {
            "jd": 2460364.0547685,
            "fid": 2,
            "diffmaglim": 16.14109992980957
        },
        {
            "jd": 2460364.0552315,
            "fid": 2,
            "diffmaglim": 16.297000885009766
        },
        {
            "jd": 2460364.055706,
            "fid": 2,
            "diffmaglim": 16.239099502563477
        },
        {
            "jd": 2460390.9991551,
            "fid": 1,
            "diffmaglim": 19.554500579833984
        },
        {
            "jd": 2460393.0022106,
            "fid": 1,
            "diffmaglim": 18.331300735473633
        },
        {
            "jd": 2460398.9740856,
            "fid": 2,
            "diffmaglim": 19.335800170898438
        },
        {
            "jd": 2460408.9500579,
            "fid": 2,
            "diffmaglim": 20.00119972229004
        },
        {
            "jd": 2460423.9529167,
            "fid": 2,
            "diffmaglim": 19.833599090576172
        },
        {
            "jd": 2460423.9687269,
            "fid": 1,
            "diffmaglim": 19.583999633789062
        },
        {
            "jd": 2460430.9651505,
            "fid": 1,
            "diffmaglim": 20.185800552368164
        },
        {
            "jd": 2460433.941956,
            "fid": 2,
            "diffmaglim": 20.748300552368164
        },
        {
            "jd": 2460444.9346065,
            "fid": 2,
            "diffmaglim": 20.65250015258789
        },
        {
            "jd": 2460444.9607176,
            "fid": 1,
            "diffmaglim": 20.718000411987305
        },
        {
            "jd": 2460447.8785532,
            "fid": 2,
            "diffmaglim": 20.36639976501465
        },
        {
            "jd": 2460452.9583565,
            "fid": 1,
            "diffmaglim": 19.85059928894043
        },
        {
            "jd": 2460457.8807176,
            "fid": 2,
            "diffmaglim": 19.899700164794922
        },
        {
            "jd": 2460457.9203009,
            "fid": 1,
            "diffmaglim": 19.891599655151367
        },
        {
            "jd": 2460459.9006713,
            "fid": 2,
            "diffmaglim": 20.196699142456055
        },
        {
            "jd": 2460461.8917477,
            "fid": 2,
            "diffmaglim": 20.776399612426758
        },
        {
            "jd": 2460461.956956,
            "fid": 1,
            "diffmaglim": 20.43869972229004
        },
        {
            "jd": 2460463.9025,
            "fid": 2,
            "diffmaglim": 20.66629981994629
        },
        {
            "jd": 2460469.9051389,
            "fid": 2,
            "diffmaglim": 20.472999572753906
        },
        {
            "jd": 2460469.9561574,
            "fid": 1,
            "diffmaglim": 20.627599716186523
        },
        {
            "jd": 2460476.9550231,
            "fid": 2,
            "diffmaglim": 20.793100357055664
        },
        {
            "jd": 2460479.8583333,
            "fid": 2,
            "diffmaglim": 19.91900062561035
        },
        {
            "jd": 2460481.9169444,
            "fid": 1,
            "diffmaglim": 19.9596004486084
        },
        {
            "jd": 2460483.8553588,
            "fid": 2,
            "diffmaglim": 19.536100387573242
        },
        {
            "jd": 2460483.898669,
            "fid": 1,
            "diffmaglim": 19.489500045776367
        },
        {
            "jd": 2460485.8684028,
            "fid": 2,
            "diffmaglim": 19.812599182128906
        },
        {
            "jd": 2460485.9160301,
            "fid": 1,
            "diffmaglim": 19.543100357055664
        },
        {
            "jd": 2460488.8694097,
            "fid": 2,
            "diffmaglim": 20.618200302124023
        },
        {
            "jd": 2460490.8928819,
            "fid": 2,
            "diffmaglim": 20.588899612426758
        },
        {
            "jd": 2460494.9148495,
            "fid": 1,
            "diffmaglim": 20.75040054321289
        },
        {
            "jd": 2460500.8581134,
            "fid": 2,
            "diffmaglim": 20.48699951171875
        },
        {
            "jd": 2460502.7976273,
            "fid": 1,
            "diffmaglim": 20.677000045776367
        },
        {
            "jd": 2460502.8583912,
            "fid": 2,
            "diffmaglim": 20.640600204467773
        },
        {
            "jd": 2460504.856794,
            "fid": 2,
            "diffmaglim": 20.590499877929688
        },
        {
            "jd": 2460507.8597338,
            "fid": 2,
            "diffmaglim": 20.477800369262695
        },
        {
            "jd": 2460509.7953935,
            "fid": 2,
            "diffmaglim": 19.827499389648438
        },
        {
            "jd": 2460512.8401273,
            "fid": 2,
            "diffmaglim": 14.665399551391602
        },
        {
            "jd": 2460515.7965162,
            "fid": 1,
            "diffmaglim": 19.409900665283203
        },
        {
            "jd": 2460515.8652894,
            "fid": 2,
            "diffmaglim": 19.541400909423828
        },
        {
            "jd": 2460518.7949537,
            "fid": 2,
            "diffmaglim": 20.6299991607666
        },
        {
            "jd": 2460520.8603125,
            "fid": 2,
            "diffmaglim": 20.550199508666992
        },
        {
            "jd": 2460522.7841204,
            "fid": 2,
            "diffmaglim": 20.476299285888672
        },
        {
            "jd": 2460522.8520139,
            "fid": 1,
            "diffmaglim": 20.48780059814453
        },
        {
            "jd": 2460525.7325231,
            "fid": 1,
            "diffmaglim": 20.666000366210938
        },
        {
            "jd": 2460525.7739815,
            "fid": 2,
            "diffmaglim": 20.767000198364258
        },
        {
            "jd": 2460527.7558449,
            "fid": 2,
            "diffmaglim": 20.721099853515625
        },
        {
            "jd": 2460527.7963773,
            "fid": 1,
            "diffmaglim": 20.590999603271484
        },
        {
            "jd": 2460529.7897801,
            "fid": 2,
            "diffmaglim": 20.802400588989258
        },
        {
            "jd": 2460531.7545833,
            "fid": 2,
            "diffmaglim": 20.70319938659668
        },
        {
            "jd": 2460535.7764931,
            "fid": 2,
            "diffmaglim": 20.626300811767578
        },
        {
            "jd": 2460535.8106829,
            "fid": 1,
            "diffmaglim": 20.656099319458008
        },
        {
            "jd": 2460537.7981366,
            "fid": 2,
            "diffmaglim": 20.412799835205078
        },
        {
            "jd": 2460537.8377778,
            "fid": 1,
            "diffmaglim": 20.27429962158203
        },
        {
            "jd": 2460539.8111574,
            "fid": 2,
            "diffmaglim": 19.33139991760254
        },
        {
            "jd": 2460543.7911806,
            "fid": 2,
            "diffmaglim": 20.024900436401367
        },
        {
            "jd": 2460543.8121875,
            "fid": 1,
            "diffmaglim": 19.663700103759766
        },
        {
            "jd": 2460545.7584491,
            "fid": 2,
            "diffmaglim": 20.16119956970215
        },
        {
            "jd": 2460547.8179398,
            "fid": 1,
            "diffmaglim": 19.992599487304688
        },
        {
            "jd": 2460549.7266782,
            "fid": 2,
            "diffmaglim": 20.84779930114746
        },
        {
            "jd": 2460549.7978009,
            "fid": 1,
            "diffmaglim": 20.50429916381836
        },
        {
            "jd": 2460551.7465162,
            "fid": 2,
            "diffmaglim": 20.61370086669922
        },
        {
            "jd": 2460551.7795833,
            "fid": 1,
            "diffmaglim": 20.60700035095215
        },
        {
            "jd": 2460553.8329861,
            "fid": 2,
            "diffmaglim": 20.348100662231445
        },
        {
            "jd": 2460556.7816435,
            "fid": 2,
            "diffmaglim": 20.610599517822266
        },
        {
            "jd": 2460558.7084838,
            "fid": 2,
            "diffmaglim": 20.66360092163086
        },
        {
            "jd": 2460558.7488889,
            "fid": 1,
            "diffmaglim": 20.78420066833496
        },
        {
            "jd": 2460562.6869097,
            "fid": 2,
            "diffmaglim": 20.5039005279541
        },
        {
            "jd": 2460562.7284954,
            "fid": 1,
            "diffmaglim": 20.494699478149414
        }
    ],
    "forcedphot": [
        {
            "objectid": "ZTF19abcudso",
            "jd": 2460352.0699537,
            "ranr": 299.333302,
            "decnr": 9.5256877,
            "fid": 2,
            "forcediffimflux": -272.2499084472656,
            "forcediffimfluxunc": 281.9033508300781,
            "magzpsci": 26.2992000579834
        },
        {
            "objectid": "ZTF19abcudso",
            "jd": 2460353.0691435,
            "ranr": 299.333302,
            "decnr": 9.5256877,
            "fid": 2,
            "forcediffimflux": 243.36888122558594,
            "forcediffimfluxunc": 314.9815979003906,
            "magzpsci": 26.312700271606445
        },
        {
            "objectid": "ZTF19abcudso",
            "jd": 2460354.0684028,
            "ranr": 299.333302,
            "decnr": 9.5256877,
            "fid": 2,
            "forcediffimflux": 379.12091064453125,
            "forcediffimfluxunc": 204.14739990234375,
            "magzpsci": 26.34830093383789
        },
        {
            "objectid": "ZTF19abcudso",
            "jd": 2460355.0653935,
            "ranr": 299.3332963,
            "decnr": 9.5257072,
            "fid": 2,
            "forcediffimflux": 166.3272705078125,
            "forcediffimfluxunc": 115.68646240234375,
            "magzpsci": 26.22170066833496
        },
        {
            "objectid": "ZTF19abcudso",
            "jd": 2460356.0645255,
            "ranr": -99999.0,
            "decnr": -99999.0,
            "fid": 2,
            "forcediffimflux": -99999.0,
            "forcediffimfluxunc": -99999.0,
            "magzpsci": 26.277599334716797
        },
        {
            "objectid": "ZTF19abcudso",
            "jd": 2460357.0664583,
            "ranr": -99999.0,
            "decnr": -99999.0,
            "fid": 2,
            "forcediffimflux": -99999.0,
            "forcediffimfluxunc": -99999.0,
            "magzpsci": 26.26959991455078
        },
        {
            "objectid": "ZTF19abcudso",
            "jd": 2460358.063669,
            "ranr": -99999.0,
            "decnr": -99999.0,
            "fid": 2,
            "forcediffimflux": -99999.0,
            "forcediffimfluxunc": -99999.0,
            "magzpsci": 26.243600845336914
        },
        {
            "objectid": "ZTF19abcudso",
            "jd": 2460369.0469097,
            "ranr": 299.333302,
            "decnr": 9.5256877,
            "fid": 2,
            "forcediffimflux": 473.9685363769531,
            "forcediffimfluxunc": 76.23123931884766,
            "magzpsci": 26.29759979248047
        },
        {
            "objectid": "ZTF19abcudso",
            "jd": 2460369.0473727,
            "ranr": 299.333302,
            "decnr": 9.5256877,
            "fid": 2,
            "forcediffimflux": 536.7887573242188,
            "forcediffimfluxunc": 72.51615905761719,
            "magzpsci": 26.304000854492188
        },
        {
            "objectid": "ZTF19abcudso",
            "jd": 2460369.0478472,
            "ranr": 299.333302,
            "decnr": 9.5256877,
            "fid": 2,
            "forcediffimflux": 450.28204345703125,
            "forcediffimfluxunc": 77.47639465332031,
            "magzpsci": 26.305200576782227
        },
        {
            "objectid": "ZTF19abcudso",
            "jd": 2460390.9991551,
            "ranr": 299.3332897,
            "decnr": 9.5257068,
            "fid": 1,
            "forcediffimflux": 281.6468811035156,
            "forcediffimfluxunc": 52.64713668823242,
            "magzpsci": 26.15220069885254
        },
        {
            "objectid": "ZTF19abcudso",
            "jd": 2460398.9740856,
            "ranr": 299.3332963,
            "decnr": 9.5257072,
            "fid": 2,
            "forcediffimflux": 381.1777038574219,
            "forcediffimfluxunc": 82.77197265625,
            "magzpsci": 26.273300170898438
        },
        {
            "objectid": "ZTF19abcudso",
            "jd": 2460404.9903241,
            "ranr": 299.3332963,
            "decnr": 9.5257072,
            "fid": 2,
            "forcediffimflux": 309.4713439941406,
            "forcediffimfluxunc": 33.5174446105957,
            "magzpsci": 26.33449935913086
        },
        {
            "objectid": "ZTF19abcudso",
            "jd": 2460408.9500579,
            "ranr": 299.3332963,
            "decnr": 9.5257072,
            "fid": 2,
            "forcediffimflux": 316.2840270996094,
            "forcediffimfluxunc": 41.275047302246094,
            "magzpsci": 26.230100631713867
        },
        {
            "objectid": "ZTF19abcudso",
            "jd": 2460420.9020486,
            "ranr": 299.3332963,
            "decnr": 9.5257072,
            "fid": 2,
            "forcediffimflux": 433.2849426269531,
            "forcediffimfluxunc": 63.472660064697266,
            "magzpsci": 26.229299545288086
        },
        {
            "objectid": "ZTF19abcudso",
            "jd": 2460420.9665856,
            "ranr": 299.3332897,
            "decnr": 9.5257068,
            "fid": 1,
            "forcediffimflux": 469.659912109375,
            "forcediffimfluxunc": 46.230716705322266,
            "magzpsci": 26.353200912475586
        },
        {
            "objectid": "ZTF19abcudso",
            "jd": 2460423.9529167,
            "ranr": 299.3332963,
            "decnr": 9.5257072,
            "fid": 2,
            "forcediffimflux": 538.33935546875,
            "forcediffimfluxunc": 54.62110900878906,
            "magzpsci": 26.332500457763672
        },
        {
            "objectid": "ZTF19abcudso",
            "jd": 2460423.9687269,
            "ranr": 299.3332897,
            "decnr": 9.5257068,
            "fid": 1,
            "forcediffimflux": 558.1009521484375,
            "forcediffimfluxunc": 70.28642272949219,
            "magzpsci": 26.375900268554688
        },
        {
            "objectid": "ZTF19abcudso",
            "jd": 2460430.9651505,
            "ranr": 299.3332897,
            "decnr": 9.5257068,
            "fid": 1,
            "forcediffimflux": 604.1481323242188,
            "forcediffimfluxunc": 42.75757598876953,
            "magzpsci": 26.389699935913086
        },
        {
            "objectid": "ZTF19abcudso",
            "jd": 2460433.941956,
            "ranr": 299.3332963,
            "decnr": 9.5257072,
            "fid": 2,
            "forcediffimflux": 538.7448120117188,
            "forcediffimfluxunc": 27.675514221191406,
            "magzpsci": 26.284799575805664
        },
        {
            "objectid": "ZTF19abcudso",
            "jd": 2460433.9677315,
            "ranr": 299.3332897,
            "decnr": 9.5257068,
            "fid": 1,
            "forcediffimflux": 532.0161743164062,
            "forcediffimfluxunc": 23.669273376464844,
            "magzpsci": 26.34630012512207
        },
        {
            "objectid": "ZTF19abcudso",
            "jd": 2460441.9260648,
            "ranr": 299.3332963,
            "decnr": 9.5257072,
            "fid": 2,
            "forcediffimflux": 563.2510375976562,
            "forcediffimfluxunc": 42.46992874145508,
            "magzpsci": 26.332199096679688
        },
        {
            "objectid": "ZTF19abcudso",
            "jd": 2460441.9700694,
            "ranr": 299.3332897,
            "decnr": 9.5257068,
            "fid": 1,
            "forcediffimflux": 524.2109985351562,
            "forcediffimfluxunc": 32.827457427978516,
            "magzpsci": 26.413700103759766
        },
        {
            "objectid": "ZTF19abcudso",
            "jd": 2460444.9346065,
            "ranr": 299.3332963,
            "decnr": 9.5257072,
            "fid": 2,
            "forcediffimflux": 474.2150573730469,
            "forcediffimfluxunc": 28.743680953979492,
            "magzpsci": 26.358299255371094
        },
        {
            "objectid": "ZTF19abcudso",
            "jd": 2460444.9607176,
            "ranr": 299.3332897,
            "decnr": 9.5257068,
            "fid": 1,
            "forcediffimflux": 484.14227294921875,
            "forcediffimfluxunc": 29.724193572998047,
            "magzpsci": 26.41320037841797
        },
        {
            "objectid": "ZTF19abcudso",
            "jd": 2460447.8785532,
            "ranr": 299.3332963,
            "decnr": 9.5257072,
            "fid": 2,
            "forcediffimflux": 388.9527893066406,
            "forcediffimfluxunc": 32.16023635864258,
            "magzpsci": 26.306100845336914
        },
        {
            "objectid": "ZTF19abcudso",
            "jd": 2460450.9021644,
            "ranr": 299.3332963,
            "decnr": 9.5257072,
            "fid": 2,
            "forcediffimflux": 511.4111022949219,
            "forcediffimfluxunc": 53.67688751220703,
            "magzpsci": 26.34000015258789
        },
        {
            "objectid": "ZTF19abcudso",
            "jd": 2460452.9055208,
            "ranr": 299.3332963,
            "decnr": 9.5257072,
            "fid": 2,
            "forcediffimflux": 415.719482421875,
            "forcediffimfluxunc": 61.139034271240234,
            "magzpsci": 26.237899780273438
        },
        {
            "objectid": "ZTF19abcudso",
            "jd": 2460452.9583565,
            "ranr": 299.3332897,
            "decnr": 9.5257068,
            "fid": 1,
            "forcediffimflux": 426.1351013183594,
            "forcediffimfluxunc": 49.66842269897461,
            "magzpsci": 26.328899383544922
        },
        {
            "objectid": "ZTF19abcudso",
            "jd": 2460457.8807176,
            "ranr": 299.3332963,
            "decnr": 9.5257072,
            "fid": 2,
            "forcediffimflux": 539.802734375,
            "forcediffimfluxunc": 48.730045318603516,
            "magzpsci": 26.295499801635742
        },
        {
            "objectid": "ZTF19abcudso",
            "jd": 2460457.9203009,
            "ranr": 299.3332897,
            "decnr": 9.5257068,
            "fid": 1,
            "forcediffimflux": 467.7548828125,
            "forcediffimfluxunc": 53.69286346435547,
            "magzpsci": 26.331499099731445
        },
        {
            "objectid": "ZTF19abcudso",
            "jd": 2460459.9006713,
            "ranr": 299.3332963,
            "decnr": 9.5257072,
            "fid": 2,
            "forcediffimflux": 487.86346435546875,
            "forcediffimfluxunc": 43.71347427368164,
            "magzpsci": 26.328500747680664
        },
        {
            "objectid": "ZTF19abcudso",
            "jd": 2460459.9267014,
            "ranr": 299.3332897,
            "decnr": 9.5257068,
            "fid": 1,
            "forcediffimflux": 493.15533447265625,
            "forcediffimfluxunc": 48.32829666137695,
            "magzpsci": 26.38759994506836
        },
        {
            "objectid": "ZTF19abcudso",
            "jd": 2460461.8917477,
            "ranr": 299.3332963,
            "decnr": 9.5257072,
            "fid": 2,
            "forcediffimflux": 480.7452697753906,
            "forcediffimfluxunc": 24.916704177856445,
            "magzpsci": 26.317800521850586
        },
        {
            "objectid": "ZTF19abcudso",
            "jd": 2460461.956956,
            "ranr": 299.3332897,
            "decnr": 9.5257068,
            "fid": 1,
            "forcediffimflux": 486.18841552734375,
            "forcediffimfluxunc": 36.5003547668457,
            "magzpsci": 26.394500732421875
        },
        {
            "objectid": "ZTF19abcudso",
            "jd": 2460463.9025,
            "ranr": 299.3332963,
            "decnr": 9.5257072,
            "fid": 2,
            "forcediffimflux": 448.19757080078125,
            "forcediffimfluxunc": 28.04010581970215,
            "magzpsci": 26.33099937438965
        },
        {
            "objectid": "ZTF19abcudso",
            "jd": 2460463.9415278,
            "ranr": 299.3332897,
            "decnr": 9.5257068,
            "fid": 1,
            "forcediffimflux": 447.76019287109375,
            "forcediffimfluxunc": 33.3062744140625,
            "magzpsci": 26.423500061035156
        },
        {
            "objectid": "ZTF19abcudso",
            "jd": 2460469.9051389,
            "ranr": 299.3332963,
            "decnr": 9.5257072,
            "fid": 2,
            "forcediffimflux": 367.8426208496094,
            "forcediffimfluxunc": 33.445125579833984,
            "magzpsci": 26.330699920654297
        },
        {
            "objectid": "ZTF19abcudso",
            "jd": 2460469.9561574,
            "ranr": 299.3332897,
            "decnr": 9.5257068,
            "fid": 1,
            "forcediffimflux": 374.94366455078125,
            "forcediffimfluxunc": 28.37837791442871,
            "magzpsci": 26.3799991607666
        },
        {
            "objectid": "ZTF19abcudso",
            "jd": 2460472.8782639,
            "ranr": 299.3332963,
            "decnr": 9.5257072,
            "fid": 2,
            "forcediffimflux": 423.50146484375,
            "forcediffimfluxunc": 30.345659255981445,
            "magzpsci": 26.354700088500977
        },
        {
            "objectid": "ZTF19abcudso",
            "jd": 2460472.9417245,
            "ranr": 299.3332897,
            "decnr": 9.5257068,
            "fid": 1,
            "forcediffimflux": 407.41961669921875,
            "forcediffimfluxunc": 29.672304153442383,
            "magzpsci": 26.398500442504883
        },
        {
            "objectid": "ZTF19abcudso",
            "jd": 2460474.8876968,
            "ranr": 299.3332963,
            "decnr": 9.5257072,
            "fid": 2,
            "forcediffimflux": 406.68145751953125,
            "forcediffimfluxunc": 34.80024337768555,
            "magzpsci": 26.362300872802734
        },
        {
            "objectid": "ZTF19abcudso",
            "jd": 2460474.9223495,
            "ranr": 299.3332897,
            "decnr": 9.5257068,
            "fid": 1,
            "forcediffimflux": 389.7657165527344,
            "forcediffimfluxunc": 33.40898513793945,
            "magzpsci": 26.418899536132812
        },
        {
            "objectid": "ZTF19abcudso",
            "jd": 2460476.878831,
            "ranr": 299.3332897,
            "decnr": 9.5257068,
            "fid": 1,
            "forcediffimflux": 428.4604187011719,
            "forcediffimfluxunc": 27.92892837524414,
            "magzpsci": 26.431400299072266
        },
        {
            "objectid": "ZTF19abcudso",
            "jd": 2460476.9550231,
            "ranr": 299.3332963,
            "decnr": 9.5257072,
            "fid": 2,
            "forcediffimflux": 445.0262756347656,
            "forcediffimfluxunc": 27.759408950805664,
            "magzpsci": 26.40019989013672
        },
        {
            "objectid": "ZTF19abcudso",
            "jd": 2460479.8583333,
            "ranr": 299.3332963,
            "decnr": 9.5257072,
            "fid": 2,
            "forcediffimflux": 315.35455322265625,
            "forcediffimfluxunc": 48.67649841308594,
            "magzpsci": 26.384300231933594
        },
        {
            "objectid": "ZTF19abcudso",
            "jd": 2460479.9000463,
            "ranr": 299.3332897,
            "decnr": 9.5257068,
            "fid": 1,
            "forcediffimflux": 327.44415283203125,
            "forcediffimfluxunc": 43.34938430786133,
            "magzpsci": 26.427799224853516
        },
        {
            "objectid": "ZTF19abcudso",
            "jd": 2460481.9169444,
            "ranr": 299.3332897,
            "decnr": 9.5257068,
            "fid": 1,
            "forcediffimflux": 417.2249755859375,
            "forcediffimfluxunc": 51.53518295288086,
            "magzpsci": 26.450899124145508
        },
        {
            "objectid": "ZTF19abcudso",
            "jd": 2460483.8553588,
            "ranr": 299.3332963,
            "decnr": 9.5257072,
            "fid": 2,
            "forcediffimflux": 254.20664978027344,
            "forcediffimfluxunc": 71.76054382324219,
            "magzpsci": 26.379199981689453
        },
        {
            "objectid": "ZTF19abcudso",
            "jd": 2460483.898669,
            "ranr": 299.3332897,
            "decnr": 9.5257068,
            "fid": 1,
            "forcediffimflux": 453.5260925292969,
            "forcediffimfluxunc": 81.80149841308594,
            "magzpsci": 26.45549964904785
        },
        {
            "objectid": "ZTF19abcudso",
            "jd": 2460485.8684028,
            "ranr": 299.3332963,
            "decnr": 9.5257072,
            "fid": 2,
            "forcediffimflux": 414.49517822265625,
            "forcediffimfluxunc": 57.030765533447266,
            "magzpsci": 26.33060073852539
        },
        {
            "objectid": "ZTF19abcudso",
            "jd": 2460485.9160301,
            "ranr": 299.3332897,
            "decnr": 9.5257068,
            "fid": 1,
            "forcediffimflux": 451.5218200683594,
            "forcediffimfluxunc": 70.15867614746094,
            "magzpsci": 26.390199661254883
        },
        {
            "objectid": "ZTF19abcudso",
            "jd": 2460488.8694097,
            "ranr": 299.3332963,
            "decnr": 9.5257072,
            "fid": 2,
            "forcediffimflux": 464.13507080078125,
            "forcediffimfluxunc": 30.858366012573242,
            "magzpsci": 26.360300064086914
        },
        {
            "objectid": "ZTF19abcudso",
            "jd": 2460490.8750579,
            "ranr": 299.3332897,
            "decnr": 9.5257068,
            "fid": 1,
            "forcediffimflux": 451.3316345214844,
            "forcediffimfluxunc": 33.6585807800293,
            "magzpsci": 26.4424991607666
        },
        {
            "objectid": "ZTF19abcudso",
            "jd": 2460490.8928819,
            "ranr": 299.3332963,
            "decnr": 9.5257072,
            "fid": 2,
            "forcediffimflux": 440.5697021484375,
            "forcediffimfluxunc": 31.112812042236328,
            "magzpsci": 26.387100219726562
        },
        {
            "objectid": "ZTF19abcudso",
            "jd": 2460494.8570949,
            "ranr": 299.3332963,
            "decnr": 9.5257072,
            "fid": 2,
            "forcediffimflux": 394.1651916503906,
            "forcediffimfluxunc": 29.96503448486328,
            "magzpsci": 26.372299194335938
        },
        {
            "objectid": "ZTF19abcudso",
            "jd": 2460494.9148495,
            "ranr": 299.3332897,
            "decnr": 9.5257068,
            "fid": 1,
            "forcediffimflux": 309.1655578613281,
            "forcediffimfluxunc": 26.898000717163086,
            "magzpsci": 26.408000946044922
        },
        {
            "objectid": "ZTF19abcudso",
            "jd": 2460500.8537037,
            "ranr": 299.3332897,
            "decnr": 9.5257068,
            "fid": 1,
            "forcediffimflux": 359.0506286621094,
            "forcediffimfluxunc": 34.72490692138672,
            "magzpsci": 26.385099411010742
        },
        {
            "objectid": "ZTF19abcudso",
            "jd": 2460500.8581134,
            "ranr": 299.3332963,
            "decnr": 9.5257072,
            "fid": 2,
            "forcediffimflux": 318.168701171875,
            "forcediffimfluxunc": 29.404565811157227,
            "magzpsci": 26.341699600219727
        },
        {
            "objectid": "ZTF19abcudso",
            "jd": 2460502.7976273,
            "ranr": 299.3332897,
            "decnr": 9.5257068,
            "fid": 1,
            "forcediffimflux": 194.86180114746094,
            "forcediffimfluxunc": 23.916696548461914,
            "magzpsci": 26.1914005279541
        },
        {
            "objectid": "ZTF19abcudso",
            "jd": 2460502.8583912,
            "ranr": 299.3332963,
            "decnr": 9.5257072,
            "fid": 2,
            "forcediffimflux": 202.4164276123047,
            "forcediffimfluxunc": 24.042552947998047,
            "magzpsci": 26.251800537109375
        },
        {
            "objectid": "ZTF19abcudso",
            "jd": 2460504.856794,
            "ranr": 299.3332963,
            "decnr": 9.5257072,
            "fid": 2,
            "forcediffimflux": 276.72900390625,
            "forcediffimfluxunc": 27.12874984741211,
            "magzpsci": 26.26180076599121
        },
        {
            "objectid": "ZTF19abcudso",
            "jd": 2460507.8543403,
            "ranr": 299.3332897,
            "decnr": 9.5257068,
            "fid": 1,
            "forcediffimflux": 264.0528259277344,
            "forcediffimfluxunc": 27.277616500854492,
            "magzpsci": 26.378799438476562
        },
        {
            "objectid": "ZTF19abcudso",
            "jd": 2460507.8597338,
            "ranr": 299.3332963,
            "decnr": 9.5257072,
            "fid": 2,
            "forcediffimflux": 247.5258026123047,
            "forcediffimfluxunc": 31.125885009765625,
            "magzpsci": 26.34469985961914
        },
        {
            "objectid": "ZTF19abcudso",
            "jd": 2460509.7953935,
            "ranr": 299.3332963,
            "decnr": 9.5257072,
            "fid": 2,
            "forcediffimflux": 272.83172607421875,
            "forcediffimfluxunc": 50.646732330322266,
            "magzpsci": 26.26799964904785
        },
        {
            "objectid": "ZTF19abcudso",
            "jd": 2460509.9317014,
            "ranr": 299.3332897,
            "decnr": 9.5257068,
            "fid": 1,
            "forcediffimflux": 227.7969207763672,
            "forcediffimfluxunc": 27.880577087402344,
            "magzpsci": 26.23189926147461
        },
        {
            "objectid": "ZTF19abcudso",
            "jd": 2460515.7965162,
            "ranr": 299.3332897,
            "decnr": 9.5257068,
            "fid": 1,
            "forcediffimflux": 308.0438232421875,
            "forcediffimfluxunc": 70.81424713134766,
            "magzpsci": 26.315399169921875
        },
        {
            "objectid": "ZTF19abcudso",
            "jd": 2460515.8652894,
            "ranr": 299.3332963,
            "decnr": 9.5257072,
            "fid": 2,
            "forcediffimflux": 191.5137939453125,
            "forcediffimfluxunc": 63.05427169799805,
            "magzpsci": 26.2278995513916
        },
        {
            "objectid": "ZTF19abcudso",
            "jd": 2460518.7949537,
            "ranr": 299.3332963,
            "decnr": 9.5257072,
            "fid": 2,
            "forcediffimflux": 159.33740234375,
            "forcediffimfluxunc": 28.76285743713379,
            "magzpsci": 26.343299865722656
        },
        {
            "objectid": "ZTF19abcudso",
            "jd": 2460518.9137731,
            "ranr": 299.3332897,
            "decnr": 9.5257068,
            "fid": 1,
            "forcediffimflux": 276.55303955078125,
            "forcediffimfluxunc": 50.23281478881836,
            "magzpsci": 26.36750030517578
        },
        {
            "objectid": "ZTF19abcudso",
            "jd": 2460520.8603125,
            "ranr": 299.3332963,
            "decnr": 9.5257072,
            "fid": 2,
            "forcediffimflux": 230.5943603515625,
            "forcediffimfluxunc": 30.494747161865234,
            "magzpsci": 26.37179946899414
        },
        {
            "objectid": "ZTF19abcudso",
            "jd": 2460522.7841204,
            "ranr": 299.3332963,
            "decnr": 9.5257072,
            "fid": 2,
            "forcediffimflux": 269.3093566894531,
            "forcediffimfluxunc": 28.43792152404785,
            "magzpsci": 26.283300399780273
        },
        {
            "objectid": "ZTF19abcudso",
            "jd": 2460522.8520139,
            "ranr": 299.3332897,
            "decnr": 9.5257068,
            "fid": 1,
            "forcediffimflux": 197.00692749023438,
            "forcediffimfluxunc": 29.24498176574707,
            "magzpsci": 26.26140022277832
        },
        {
            "objectid": "ZTF19abcudso",
            "jd": 2460525.7325231,
            "ranr": 299.3332897,
            "decnr": 9.5257068,
            "fid": 1,
            "forcediffimflux": 298.64605712890625,
            "forcediffimfluxunc": 26.12447738647461,
            "magzpsci": 26.343900680541992
        },
        {
            "objectid": "ZTF19abcudso",
            "jd": 2460525.7739815,
            "ranr": 299.3332963,
            "decnr": 9.5257072,
            "fid": 2,
            "forcediffimflux": 230.52841186523438,
            "forcediffimfluxunc": 23.092025756835938,
            "magzpsci": 26.343399047851562
        },
        {
            "objectid": "ZTF19abcudso",
            "jd": 2460527.7558449,
            "ranr": 299.3332963,
            "decnr": 9.5257072,
            "fid": 2,
            "forcediffimflux": 315.5350036621094,
            "forcediffimfluxunc": 27.16397476196289,
            "magzpsci": 26.320199966430664
        },
        {
            "objectid": "ZTF19abcudso",
            "jd": 2460527.7963773,
            "ranr": 299.3332897,
            "decnr": 9.5257068,
            "fid": 1,
            "forcediffimflux": 300.1424560546875,
            "forcediffimfluxunc": 27.35836410522461,
            "magzpsci": 26.37540054321289
        },
        {
            "objectid": "ZTF19abcudso",
            "jd": 2460529.7897801,
            "ranr": 299.3332963,
            "decnr": 9.5257072,
            "fid": 2,
            "forcediffimflux": 287.4823303222656,
            "forcediffimfluxunc": 23.646854400634766,
            "magzpsci": 26.300399780273438
        },
        {
            "objectid": "ZTF19abcudso",
            "jd": 2460529.7950926,
            "ranr": 299.3332897,
            "decnr": 9.5257068,
            "fid": 1,
            "forcediffimflux": 280.3079833984375,
            "forcediffimfluxunc": 27.667884826660156,
            "magzpsci": 26.327199935913086
        },
        {
            "objectid": "ZTF19abcudso",
            "jd": 2460531.7545833,
            "ranr": 299.3332963,
            "decnr": 9.5257072,
            "fid": 2,
            "forcediffimflux": 306.08111572265625,
            "forcediffimfluxunc": 26.10220718383789,
            "magzpsci": 26.305299758911133
        },
        {
            "objectid": "ZTF19abcudso",
            "jd": 2460531.7975463,
            "ranr": 299.3332897,
            "decnr": 9.5257068,
            "fid": 1,
            "forcediffimflux": 275.7397155761719,
            "forcediffimfluxunc": 27.071550369262695,
            "magzpsci": 26.348499298095703
        },
        {
            "objectid": "ZTF19abcudso",
            "jd": 2460535.7764931,
            "ranr": 299.3332963,
            "decnr": 9.5257072,
            "fid": 2,
            "forcediffimflux": 341.84783935546875,
            "forcediffimfluxunc": 29.46603012084961,
            "magzpsci": 26.37540054321289
        },
        {
            "objectid": "ZTF19abcudso",
            "jd": 2460535.8106829,
            "ranr": 299.3332897,
            "decnr": 9.5257068,
            "fid": 1,
            "forcediffimflux": 316.4265441894531,
            "forcediffimfluxunc": 28.99896240234375,
            "magzpsci": 26.43869972229004
        },
        {
            "objectid": "ZTF19abcudso",
            "jd": 2460537.7981366,
            "ranr": 299.3332963,
            "decnr": 9.5257072,
            "fid": 2,
            "forcediffimflux": 369.75848388671875,
            "forcediffimfluxunc": 34.15077590942383,
            "magzpsci": 26.37529945373535
        },
        {
            "objectid": "ZTF19abcudso",
            "jd": 2460537.8377778,
            "ranr": 299.3332897,
            "decnr": 9.5257068,
            "fid": 1,
            "forcediffimflux": 333.53460693359375,
            "forcediffimfluxunc": 41.387752532958984,
            "magzpsci": 26.41710090637207
        },
        {
            "objectid": "ZTF19abcudso",
            "jd": 2460539.8111574,
            "ranr": 299.3332963,
            "decnr": 9.5257072,
            "fid": 2,
            "forcediffimflux": 138.818603515625,
            "forcediffimfluxunc": 82.4931640625,
            "magzpsci": 26.31399917602539
        },
        {
            "objectid": "ZTF19abcudso",
            "jd": 2460543.7911806,
            "ranr": 299.3332963,
            "decnr": 9.5257072,
            "fid": 2,
            "forcediffimflux": 250.98695373535156,
            "forcediffimfluxunc": 45.2242546081543,
            "magzpsci": 26.368900299072266
        },
        {
            "objectid": "ZTF19abcudso",
            "jd": 2460543.8121875,
            "ranr": 299.3332897,
            "decnr": 9.5257068,
            "fid": 1,
            "forcediffimflux": 268.0363464355469,
            "forcediffimfluxunc": 62.8137321472168,
            "magzpsci": 26.41119956970215
        },
        {
            "objectid": "ZTF19abcudso",
            "jd": 2460545.7047338,
            "ranr": 299.3332897,
            "decnr": 9.5257068,
            "fid": 1,
            "forcediffimflux": 359.50244140625,
            "forcediffimfluxunc": 46.03668212890625,
            "magzpsci": 26.449199676513672
        },
        {
            "objectid": "ZTF19abcudso",
            "jd": 2460545.7584491,
            "ranr": 299.3332963,
            "decnr": 9.5257072,
            "fid": 2,
            "forcediffimflux": 275.0372314453125,
            "forcediffimfluxunc": 43.20968246459961,
            "magzpsci": 26.384199142456055
        },
        {
            "objectid": "ZTF19abcudso",
            "jd": 2460547.7356019,
            "ranr": 299.3332963,
            "decnr": 9.5257072,
            "fid": 2,
            "forcediffimflux": 313.01666259765625,
            "forcediffimfluxunc": 34.420536041259766,
            "magzpsci": 26.382400512695312
        },
        {
            "objectid": "ZTF19abcudso",
            "jd": 2460547.8179398,
            "ranr": 299.3332897,
            "decnr": 9.5257068,
            "fid": 1,
            "forcediffimflux": 313.8179626464844,
            "forcediffimfluxunc": 47.66423797607422,
            "magzpsci": 26.383499145507812
        },
        {
            "objectid": "ZTF19abcudso",
            "jd": 2460549.7266782,
            "ranr": 299.3332963,
            "decnr": 9.5257072,
            "fid": 2,
            "forcediffimflux": 315.1556701660156,
            "forcediffimfluxunc": 22.36640739440918,
            "magzpsci": 26.36989974975586
        },
        {
            "objectid": "ZTF19abcudso",
            "jd": 2460549.7978009,
            "ranr": 299.3332897,
            "decnr": 9.5257068,
            "fid": 1,
            "forcediffimflux": 365.3217468261719,
            "forcediffimfluxunc": 31.631698608398438,
            "magzpsci": 26.41710090637207
        },
        {
            "objectid": "ZTF19abcudso",
            "jd": 2460551.7465162,
            "ranr": 299.3332963,
            "decnr": 9.5257072,
            "fid": 2,
            "forcediffimflux": 278.2379455566406,
            "forcediffimfluxunc": 32.007179260253906,
            "magzpsci": 26.388900756835938
        },
        {
            "objectid": "ZTF19abcudso",
            "jd": 2460551.7795833,
            "ranr": 299.3332897,
            "decnr": 9.5257068,
            "fid": 1,
            "forcediffimflux": 269.1900329589844,
            "forcediffimfluxunc": 30.570907592773438,
            "magzpsci": 26.44300079345703
        },
        {
            "objectid": "ZTF19abcudso",
            "jd": 2460553.7127546,
            "ranr": 299.3332897,
            "decnr": 9.5257068,
            "fid": 1,
            "forcediffimflux": 290.2635192871094,
            "forcediffimfluxunc": 31.65102195739746,
            "magzpsci": 26.428199768066406
        },
        {
            "objectid": "ZTF19abcudso",
            "jd": 2460553.8329861,
            "ranr": 299.3332963,
            "decnr": 9.5257072,
            "fid": 2,
            "forcediffimflux": 323.7707824707031,
            "forcediffimfluxunc": 35.75197219848633,
            "magzpsci": 26.341400146484375
        },
        {
            "objectid": "ZTF19abcudso",
            "jd": 2460556.7334491,
            "ranr": 299.3332897,
            "decnr": 9.5257068,
            "fid": 1,
            "forcediffimflux": 296.7296447753906,
            "forcediffimfluxunc": 32.86433410644531,
            "magzpsci": 26.386899948120117
        },
        {
            "objectid": "ZTF19abcudso",
            "jd": 2460556.7816435,
            "ranr": 299.3332963,
            "decnr": 9.5257072,
            "fid": 2,
            "forcediffimflux": 312.1075439453125,
            "forcediffimfluxunc": 28.10645294189453,
            "magzpsci": 26.33530044555664
        },
        {
            "objectid": "ZTF19abcudso",
            "jd": 2460558.7084838,
            "ranr": 299.3332963,
            "decnr": 9.5257072,
            "fid": 2,
            "forcediffimflux": 265.1060485839844,
            "forcediffimfluxunc": 25.827852249145508,
            "magzpsci": 26.352500915527344
        },
        {
            "objectid": "ZTF19abcudso",
            "jd": 2460558.7488889,
            "ranr": 299.3332897,
            "decnr": 9.5257068,
            "fid": 1,
            "forcediffimflux": 245.921630859375,
            "forcediffimfluxunc": 27.394174575805664,
            "magzpsci": 26.366500854492188
        },
        {
            "objectid": "ZTF19abcudso",
            "jd": 2460562.6869097,
            "ranr": 299.3332963,
            "decnr": 9.5257072,
            "fid": 2,
            "forcediffimflux": 313.6342468261719,
            "forcediffimfluxunc": 28.88434600830078,
            "magzpsci": 26.21500015258789
        },
        {
            "objectid": "ZTF19abcudso",
            "jd": 2460562.7284954,
            "ranr": 299.3332897,
            "decnr": 9.5257068,
            "fid": 1,
            "forcediffimflux": 241.6861114501953,
            "forcediffimfluxunc": 27.008975982666016,
            "magzpsci": 26.193700790405273
        }
    ]
}