{
    "objectId": "ZTF19acqxhhy",
    "candidates": [
        {
            "candid": 1983186860915010010,
            "jd": 2459737.6868634,
            "ra": 172.9647802,
            "dec": -12.5329211,
            "fid": 1,
            "nid": 1983,
            "magpsf": 19.536659240722656,
            "sigmapsf": 0.19471299648284912,
            "magnr": 17.062999725341797,
            "sigmagnr": 0.03099999949336052,
            "magzpsci": 26.266660690307617,
            "isdiffpos": "f",
            "ssdistnr": -999.0,
            "ssnamenr": "null",
            "drb": 0.9969969987869263
        },
        {
            "candid": 2289316620915010007,
            "jd": 2460043.8166204,
            "ra": 172.9648444,
            "dec": -12.5329054,
            "fid": 1,
            "nid": 2289,
            "magpsf": 18.936800003051758,
            "sigmapsf": 0.21382400393486023,
            "magnr": 17.062999725341797,
            "sigmagnr": 0.03099999949336052,
            "magzpsci": 26.059799194335938,
            "isdiffpos": "f",
            "ssdistnr": null,
            "ssnamenr": null,
            "drb": null
        },
        {
            "candid": 2298270810915010036,
            "jd": 2460052.7708102,
            "ra": 172.9648559,
            "dec": -12.532889,
            "fid": 1,
            "nid": 2298,
            "magpsf": 19.263200759887695,
            "sigmapsf": 0.15172700583934784,
            "magnr": 17.062999725341797,
            "sigmagnr": 0.03099999949336052,
            "magzpsci": 26.243200302124023,
            "isdiffpos": "f",
            "ssdistnr": null,
            "ssnamenr": null,
            "drb": null
        },
        {
            "candid": 2300253910915010024,
            "jd": 2460054.753912,
            "ra": 172.964831,
            "dec": -12.5328964,
            "fid": 1,
            "nid": 2300,
            "magpsf": 19.361799240112305,
            "sigmapsf": 0.18691499531269073,
            "magnr": 17.062999725341797,
            "sigmagnr": 0.03099999949336052,
            "magzpsci": 26.288799285888672,
            "isdiffpos": "f",
            "ssdistnr": null,
            "ssnamenr": null,
            "drb": null
        },
        {
            "candid": 2302211370915010024,
            "jd": 2460056.7113773,
            "ra": 172.9648353,
            "dec": -12.5329294,
            "fid": 1,
            "nid": 2302,
            "magpsf": 19.46940040588379,
            "sigmapsf": 0.1968500018119812,
            "magnr": 17.062999725341797,
            "sigmagnr": 0.03099999949336052,
            "magzpsci": 26.30940055847168,
            "isdiffpos": "f",
            "ssdistnr": null,
            "ssnamenr": null,
            "drb": null
        },
        {
            "candid": 2304319150915010022,
            "jd": 2460058.8191551,
            "ra": 172.9647328,
            "dec": -12.5329592,
            "fid": 1,
            "nid": 2304,
            "magpsf": 19.528078079223633,
            "sigmapsf": 0.20086301863193512,
            "magnr": 17.062999725341797,
            "sigmagnr": 0.03099999949336052,
            "magzpsci": 26.087078094482422,
            "isdiffpos": "f",
            "ssdistnr": -999.0,
            "ssnamenr": "null",
            "drb": null
        },
        {
            "candid": 2503530450915010007,
            "jd": 2460258.0304514,
            "ra": 172.965075,
            "dec": -12.5330431,
            "fid": 2,
            "nid": 2503,
            "magpsf": 18.53339958190918,
            "sigmapsf": 0.1634729951620102,
            "magnr": 17.04199981689453,
            "sigmagnr": 0.05700000002980232,
            "magzpsci": 26.14940071105957,
            "isdiffpos": "f",
            "ssdistnr": null,
            "ssnamenr": null,
            "drb": null
        },
        {
            "candid": 2503540590915010010,
            "jd": 2460258.0405903,
            "ra": 172.9649065,
            "dec": -12.5330061,
            "fid": 2,
            "nid": 2503,
            "magpsf": 18.632999420166016,
            "sigmapsf": 0.22482499480247498,
            "magnr": 17.04199981689453,
            "sigmagnr": 0.05700000002980232,
            "magzpsci": 26.165000915527344,
            "isdiffpos": "f",
            "ssdistnr": null,
            "ssnamenr": null,
            "drb": null
        },
        {
            "candid": 2504531780915010012,
            "jd": 2460259.0317824,
            "ra": 172.9648335,
            "dec": -12.5329887,
            "fid": 2,
            "nid": 2504,
            "magpsf": 18.585899353027344,
            "sigmapsf": 0.12257900089025497,
            "magnr": 17.04199981689453,
            "sigmagnr": 0.05700000002980232,
            "magzpsci": 26.14389991760254,
            "isdiffpos": "f",
            "ssdistnr": null,
            "ssnamenr": null,
            "drb": null
        },
        {
            "candid": 2504534390915010016,
            "jd": 2460259.0343981,
            "ra": 172.964935,
            "dec": -12.5329161,
            "fid": 2,
            "nid": 2504,
            "magpsf": 18.52869987487793,
            "sigmapsf": 0.12192799896001816,
            "magnr": 17.04199981689453,
            "sigmagnr": 0.05700000002980232,
            "magzpsci": 26.137699127197266,
            "isdiffpos": "f",
            "ssdistnr": null,
            "ssnamenr": null,
            "drb": null
        },
        {
            "candid": 2504537000915010013,
            "jd": 2460259.0370023,
            "ra": 172.9648882,
            "dec": -12.5328993,
            "fid": 2,
            "nid": 2504,
            "magpsf": 18.627399444580078,
            "sigmapsf": 0.10369499772787094,
            "magnr": 17.04199981689453,
            "sigmagnr": 0.05700000002980232,
            "magzpsci": 26.14539909362793,
            "isdiffpos": "f",
            "ssdistnr": null,
            "ssnamenr": null,
            "drb": null
        },
        {
            "candid": 2504539590915010012,
            "jd": 2460259.0395949,
            "ra": 172.9649733,
            "dec": -12.5329669,
            "fid": 2,
            "nid": 2504,
            "magpsf": 18.651399612426758,
            "sigmapsf": 0.1191679984331131,
            "magnr": 17.04199981689453,
            "sigmagnr": 0.05700000002980232,
            "magzpsci": 26.15839958190918,
            "isdiffpos": "f",
            "ssdistnr": null,
            "ssnamenr": null,
            "drb": null
        },
        {
            "candid": 2504542190915010007,
            "jd": 2460259.0421991,
            "ra": 172.964922,
            "dec": -12.5329655,
            "fid": 2,
            "nid": 2504,
            "magpsf": 18.654600143432617,
            "sigmapsf": 0.09866700321435928,
            "magnr": 17.04199981689453,
            "sigmagnr": 0.05700000002980232,
            "magzpsci": 26.151599884033203,
            "isdiffpos": "f",
            "ssdistnr": null,
            "ssnamenr": null,
            "drb": null
        },
        {
            "candid": 2505533850915010006,
            "jd": 2460260.0338542,
            "ra": 172.9650345,
            "dec": -12.5329202,
            "fid": 2,
            "nid": 2505,
            "magpsf": 18.549299240112305,
            "sigmapsf": 0.11604399979114532,
            "magnr": 17.04199981689453,
            "sigmagnr": 0.05700000002980232,
            "magzpsci": 26.165300369262695,
            "isdiffpos": "f",
            "ssdistnr": null,
            "ssnamenr": null,
            "drb": null
        },
        {
            "candid": 2505536370915010011,
            "jd": 2460260.0363773,
            "ra": 172.9649076,
            "dec": -12.532929,
            "fid": 2,
            "nid": 2505,
            "magpsf": 18.72439956665039,
            "sigmapsf": 0.10203400254249573,
            "magnr": 17.04199981689453,
            "sigmagnr": 0.05700000002980232,
            "magzpsci": 26.177400588989258,
            "isdiffpos": "f",
            "ssdistnr": null,
            "ssnamenr": null,
            "drb": null
        },
        {
            "candid": 2505538910915010019,
            "jd": 2460260.038912,
            "ra": 172.9648547,
            "dec": -12.5329173,
            "fid": 2,
            "nid": 2505,
            "magpsf": 18.53420066833496,
            "sigmapsf": 0.09120699763298035,
            "magnr": 17.04199981689453,
            "sigmagnr": 0.05700000002980232,
            "magzpsci": 26.184200286865234,
            "isdiffpos": "f",
            "ssdistnr": null,
            "ssnamenr": null,
            "drb": null
        },
        {
            "candid": 2505541440915010013,
            "jd": 2460260.0414468,
            "ra": 172.9649333,
            "dec": -12.5329389,
            "fid": 2,
            "nid": 2505,
            "magpsf": 18.591899871826172,
            "sigmapsf": 0.08827099949121475,
            "magnr": 17.04199981689453,
            "sigmagnr": 0.05700000002980232,
            "magzpsci": 26.17889976501465,
            "isdiffpos": "f",
            "ssdistnr": null,
            "ssnamenr": null,
            "drb": null
        },
        {
            "candid": 2505543980915010014,
            "jd": 2460260.0439815,
            "ra": 172.9649132,
            "dec": -12.5329,
            "fid": 2,
            "nid": 2505,
            "magpsf": 18.60930061340332,
            "sigmapsf": 0.08696600049734116,
            "magnr": 17.04199981689453,
            "sigmagnr": 0.05700000002980232,
            "magzpsci": 26.18429946899414,
            "isdiffpos": "f",
            "ssdistnr": null,
            "ssnamenr": null,
            "drb": null
        },
        {
            "candid": 2533481000915010013,
            "jd": 2460287.9810069,
            "ra": 172.964792,
            "dec": -12.5328898,
            "fid": 2,
            "nid": 2533,
            "magpsf": 18.67359161376953,
            "sigmapsf": 0.18167755007743835,
            "magnr": 17.04199981689453,
            "sigmagnr": 0.05700000002980232,
            "magzpsci": 26.187591552734375,
            "isdiffpos": "f",
            "ssdistnr": -999.0,
            "ssnamenr": "null",
            "drb": null
        },
        {
            "jd": 2459707.698044,
            "fid": 2,
            "diffmaglim": 19.749799728393555
        },
        {
            "jd": 2459709.6707407,
            "fid": 2,
            "diffmaglim": 19.614900588989258
        },
        {
            "jd": 2459709.7338194,
            "fid": 2,
            "diffmaglim": 19.641199111938477
        },
        {
            "jd": 2459713.6917361,
            "fid": 1,
            "diffmaglim": 18.985700607299805
        },
        {
            "jd": 2459713.7328704,
            "fid": 2,
            "diffmaglim": 19.28380012512207
        },
        {
            "jd": 2459715.6739236,
            "fid": 2,
            "diffmaglim": 20.235700607299805
        },
        {
            "jd": 2459715.7546065,
            "fid": 1,
            "diffmaglim": 18.824499130249023
        },
        {
            "jd": 2459719.6747685,
            "fid": 2,
            "diffmaglim": 20.228599548339844
        },
        {
            "jd": 2459722.6918866,
            "fid": 1,
            "diffmaglim": 20.17460060119629
        },
        {
            "jd": 2459722.7546759,
            "fid": 1,
            "diffmaglim": 19.92329978942871
        },
        {
            "jd": 2459724.6909606,
            "fid": 1,
            "diffmaglim": 20.080699920654297
        },
        {
            "jd": 2459724.732338,
            "fid": 2,
            "diffmaglim": 20.03820037841797
        },
        {
            "jd": 2459726.6791319,
            "fid": 2,
            "diffmaglim": 20.311500549316406
        },
        {
            "jd": 2459726.7117014,
            "fid": 1,
            "diffmaglim": 20.31049919128418
        },
        {
            "jd": 2459731.7319444,
            "fid": 2,
            "diffmaglim": 19.73259925842285
        },
        {
            "jd": 2459733.727037,
            "fid": 2,
            "diffmaglim": 19.8572998046875
        },
        {
            "jd": 2459735.7369676,
            "fid": 2,
            "diffmaglim": 19.962900161743164
        },
        {
            "jd": 2460031.7961806,
            "fid": 2,
            "diffmaglim": 20.020200729370117
        },
        {
            "jd": 2460036.7943866,
            "fid": 1,
            "diffmaglim": 19.271900177001953
        },
        {
            "jd": 2460045.756088,
            "fid": 2,
            "diffmaglim": 20.359899520874023
        },
        {
            "jd": 2460050.7516782,
            "fid": 2,
            "diffmaglim": 20.260299682617188
        },
        {
            "jd": 2460052.7751157,
            "fid": 2,
            "diffmaglim": 20.20509910583496
        },
        {
            "jd": 2460056.6692014,
            "fid": 2,
            "diffmaglim": 20.193300247192383
        },
        {
            "jd": 2460058.7320949,
            "fid": 2,
            "diffmaglim": 19.89240074157715
        },
        {
            "jd": 2460258.0329745,
            "fid": 2,
            "diffmaglim": 18.99720001220703
        },
        {
            "jd": 2460258.0355093,
            "fid": 2,
            "diffmaglim": 18.808700561523438
        },
        {
            "jd": 2460258.038044,
            "fid": 2,
            "diffmaglim": 18.820999145507812
        }
    ],
    "forcedphot": [
        {
            "objectid": "ZTF19acqxhhy",
            "jd": 2460259.0421991,
            "ranr": 172.9648699,
            "decnr": -12.5329157,
            "fid": 2,
            "forcediffimflux": -948.178955078125,
            "forcediffimfluxunc": 58.28290939331055,
            "magzpsci": 26.151599884033203
        },
        {
            "objectid": "ZTF19acqxhhy",
            "jd": 2460260.0439815,
            "ranr": 172.9648699,
            "decnr": -12.5329157,
            "fid": 2,
            "forcediffimflux": -1008.0087280273438,
            "forcediffimfluxunc": 47.83757781982422,
            "magzpsci": 26.18429946899414
        }
    ]
}